canvas_lms_api/__init__.py
canvas_lms_api/canvas.py
canvas_lms_api/test.py
canvas_lms_api-0.4.2.dist-info/LICENSE
canvas_lms_api-0.4.2.dist-info/METADATA
canvas_lms_api-0.4.2.dist-info/WHEEL
canvas_lms_api-0.4.2.dist-info/top_level.txt
canvas_lms_api-0.4.2.dist-info/RECORD
