Metadata-Version: 2.1
Name: canvas-lms-api
Version: 0.4.2
Summary: Pip installable canvas API used by GT classes
Home-page: https://github.gatech.edu/omscs-ta/canvas_lms_api
Author: Tyson Bailey
Author-email: tyson@onaclovtech.com
License: UNKNOWN
Platform: UNKNOWN
Classifier: Programming Language :: Python :: 3
Classifier: License :: OSI Approved :: MIT License
Classifier: Operating System :: OS Independent
Requires-Python: >=3
Requires-Dist: requests
